{
  "resourceType": "CodeSystem",
  "status": "active",
  "content": "complete",
  "name": "EEBaseOccupation",
  "id": "ee-occupation",
  "title": "Eesti ametite klassifikaator",
  "description": "Eesti ametite klassifikaator",
  "version": "0.9.0",
  "url": "https://fhir.ee/CodeSystem/ee-occupation",
  "concept": [
    {
      "code": "22122501",
      "display": "Pediaater"
    },
    {
      "code": "22121101",
      "display": "Allergoloog-immunoloog"
    },
    {
      "code": "22120901",
      "display": "Kardioloog"
    },
    {
      "code": "22210502",
      "display": "Õde"
    },
    {
      "code": "PN",
      "display": "Advanced Practice Nurse"
    }
  ],
  "experimental": true,
  "caseSensitive": false,
  "count": 5
}
